csv2http/__init__.py
csv2http/_version.py
csv2http/cli.py
csv2http/constants.py
csv2http/core.py
csv2http/parser.py
csv2http/utils.py
csv2http-0.0.3a1.dist-info/entry_points.txt
csv2http-0.0.3a1.dist-info/LICENSE
csv2http-0.0.3a1.dist-info/WHEEL
csv2http-0.0.3a1.dist-info/METADATA
csv2http-0.0.3a1.dist-info/RECORD
