Metadata-Version: 2.1
Name: csv2http
Version: 0.0.3a1
Summary: Make http requests based on a CSV input file
Home-page: https://github.com/kilo59/csv2http
License: MIT
Keywords: http,csv,cli,remediation,async
Author: Gabriel Gore
Author-email: gabriel59kg@gmail.com
Requires-Python: >=3.7.2,<4.0.0
Classifier: Development Status :: 2 - Pre-Alpha
Classifier: Environment :: Console
Classifier: License :: OSI Approved :: MIT License
Classifier: Programming Language :: Python :: 3
Classifier: Programming Language :: Python :: 3.10
Classifier: Programming Language :: Python :: 3.8
Classifier: Programming Language :: Python :: 3.9
Classifier: Topic :: Internet :: WWW/HTTP
Classifier: Topic :: Software Development :: Libraries :: Python Modules
Requires-Dist: httpx (>=0.23.0,<0.24.0)
Requires-Dist: typing-extensions (>=4.2.0,<5.0.0); python_version >= "3.7" and python_version < "3.8"
Project-URL: Repository, https://github.com/kilo59/csv2http
